alu.v
module alu (
    input wire [31:0] a,
    input wire [31:0] b,
    input wire [3:0] alu_control,
    output reg [31:0] result,
    output wire zero
);

always @(*) begin
    case (alu_control)
        4'b0000: result = a + b;
        4'b0001: result = a - b;
        4'b0010: result = a & b;
        4'b0011: result = a | b;
        4'b0100: result = a ^ b;
        4'b0101: result = a << b[4:0];
        4'b0110: result = a >> b[4:0];
        4'b0111: result = ($signed(a) < $signed(b)) ? 32'd1 : 32'd0;
        default: result = 32'b0;
    endcase
end

assign zero = (result == 32'b0);

endmodule

tb_alu.v
`timescale 1ns/1ps

module tb_alu;

reg [31:0] a;
reg [31:0] b;
reg [3:0] alu_control;

wire [31:0] result;
wire zero;

alu uut (
    .a(a),
    .b(b),
    .alu_control(alu_control),
    .result(result),
    .zero(zero)
);

initial begin
$dumpfile("alu.vcd");
$dumpvars(0, tb_alu);
    a = 32'd10;
    b = 32'd5;
    alu_control = 4'b0000;
    #10;

    a = 32'd10;
    b = 32'd5;
    alu_control = 4'b0001;
    #10;

    a = 32'hFF00;
    b = 32'h0F0F;
    alu_control = 4'b0010;
    #10;

    a = 32'hFF00;
    b = 32'h0F0F;
    alu_control = 4'b0011;
    #10;

    a = 32'hFF00;
    b = 32'h0F0F;
    alu_control = 4'b0100;
    #10;

    a = 32'd5;
    b = 32'd2;
    alu_control = 4'b0101;
    #10;

    a = 32'd20;
    b = 32'd2;
    alu_control = 4'b0110;
    #10;

    a = 32'd5;
    b = 32'd10;
    alu_control = 4'b0111;
    #10;

    $finish;

end

endmodule

alu.vcd
$date
	Sat Sep 12 03:21:51 2026
$end
$version
	Icarus Verilog
$end
$timescale
	1ps
$end
$scope module tb_alu $end
$var wire 1 ! zero $end
$var wire 32 " result [31:0] $end
$var reg 32 # a [31:0] $end
$var reg 4 $ alu_control [3:0] $end
$var reg 32 % b [31:0] $end
$scope module uut $end
$var wire 32 & a [31:0] $end
$var wire 4 ' alu_control [3:0] $end
$var wire 32 ( b [31:0] $end
$var wire 1 ! zero $end
$var reg 32 ) result [31:0] $end
$upscope $end
$upscope $end
$enddefinitions $end
$comment Show the parameter values. $end
$dumpall
$end
#0
$dumpvars
b1111 )
b101 (
b0 '
b1010 &
b101 %
b0 $
b1010 #
b1111 "
0!
$end
#10000
b101 "
b101 )
b1 $
b1 '
#20000
b111100000000 "
b111100000000 )
b10 $
b10 '
b111100001111 %
b111100001111 (
b1111111100000000 #
b1111111100000000 &
#30000
b1111111100001111 "
b1111111100001111 )
b11 $
b11 '
#40000
b1111000000001111 "
b1111000000001111 )
b100 $
b100 '
#50000
b10100 "
b10100 )
b101 $
b101 '
b10 %
b10 (
b101 #
b101 &
#60000
b101 "
b101 )
b110 $
b110 '
b10100 #
b10100 &
#70000
b1 "
b1 )
b111 $
b111 '
b1010 %
b1010 (
b101 #
b101 &
