ex_mem.v
module ex_mem (
    input wire clk,
    input wire rst,
    input wire [31:0] alu_result_in,
    input wire [31:0] write_data_in,
    input wire [31:0] branch_target_in,
    input wire zero_in,
    input wire [4:0] rd_in,
    input wire reg_write_in,
    input wire mem_read_in,
    input wire mem_write_in,
    input wire mem_to_reg_in,
    input wire branch_in,
    output reg [31:0] alu_result_out,
    output reg [31:0] write_data_out,
    output reg [31:0] branch_target_out,
    output reg zero_out,
    output reg [4:0] rd_out,
    output reg reg_write_out,
    output reg mem_read_out,
    output reg mem_write_out,
    output reg mem_to_reg_out,
    output reg branch_out
);

always @(posedge clk) begin
    if (rst) begin
        alu_result_out <= 32'b0;
        write_data_out <= 32'b0;
        branch_target_out <= 32'b0;
        zero_out <= 1'b0;
        rd_out <= 5'b0;
        reg_write_out <= 1'b0;
        mem_read_out <= 1'b0;
        mem_write_out <= 1'b0;
        mem_to_reg_out <= 1'b0;
        branch_out <= 1'b0;
    end
    else begin
        alu_result_out <= alu_result_in;
        write_data_out <= write_data_in;
        branch_target_out <= branch_target_in;
        zero_out <= zero_in;
        rd_out <= rd_in;
        reg_write_out <= reg_write_in;
        mem_read_out <= mem_read_in;
        mem_write_out <= mem_write_in;
        mem_to_reg_out <= mem_to_reg_in;
        branch_out <= branch_in;
    end
end

endmodule

tb_ex_mem.v
`timescale 1ns/1ps

module tb_ex_mem;

reg clk;
reg rst;
reg [31:0] alu_result_in;
reg [31:0] write_data_in;
reg [31:0] branch_target_in;
reg zero_in;
reg [4:0] rd_in;
reg reg_write_in;
reg mem_read_in;
reg mem_write_in;
reg mem_to_reg_in;
reg branch_in;

wire [31:0] alu_result_out;
wire [31:0] write_data_out;
wire [31:0] branch_target_out;
wire zero_out;
wire [4:0] rd_out;
wire reg_write_out;
wire mem_read_out;
wire mem_write_out;
wire mem_to_reg_out;
wire branch_out;

ex_mem uut (
    .clk(clk),
    .rst(rst),
    .alu_result_in(alu_result_in),
    .write_data_in(write_data_in),
    .branch_target_in(branch_target_in),
    .zero_in(zero_in),
    .rd_in(rd_in),
    .reg_write_in(reg_write_in),
    .mem_read_in(mem_read_in),
    .mem_write_in(mem_write_in),
    .mem_to_reg_in(mem_to_reg_in),
    .branch_in(branch_in),
    .alu_result_out(alu_result_out),
    .write_data_out(write_data_out),
    .branch_target_out(branch_target_out),
    .zero_out(zero_out),
    .rd_out(rd_out),
    .reg_write_out(reg_write_out),
    .mem_read_out(mem_read_out),
    .mem_write_out(mem_write_out),
    .mem_to_reg_out(mem_to_reg_out),
    .branch_out(branch_out)
);

always #5 clk = ~clk;

initial begin
    $dumpfile("ex_mem.vcd");
    $dumpvars(0, tb_ex_mem);

    clk = 0;
    rst = 1;
    alu_result_in = 0;
    write_data_in = 0;
    branch_target_in = 0;
    zero_in = 0;
    rd_in = 0;
    reg_write_in = 0;
    mem_read_in = 0;
    mem_write_in = 0;
    mem_to_reg_in = 0;
    branch_in = 0;

    #10;

    rst = 0;
    alu_result_in = 32'd100;
    write_data_in = 32'd25;
    branch_target_in = 32'd40;
    zero_in = 0;
    rd_in = 5'd5;
    reg_write_in = 1;
    mem_read_in = 0;
    mem_write_in = 0;
    mem_to_reg_in = 0;
    branch_in = 0;

    #10;

    alu_result_in = 32'd200;
    write_data_in = 32'd50;
    branch_target_in = 32'd80;
    zero_in = 1;
    rd_in = 5'd10;
    reg_write_in = 1;
    mem_read_in = 1;
    mem_write_in = 0;
    mem_to_reg_in = 1;
    branch_in = 0;

    #10;

    alu_result_in = 32'd300;
    write_data_in = 32'd75;
    branch_target_in = 32'd120;
    zero_in = 0;
    rd_in = 5'd15;
    reg_write_in = 0;
    mem_read_in = 0;
    mem_write_in = 1;
    mem_to_reg_in = 0;
    branch_in = 0;

    #10;

    alu_result_in = 32'd400;
    write_data_in = 32'd0;
    branch_target_in = 32'd160;
    zero_in = 1;
    rd_in = 5'd0;
    reg_write_in = 0;
    mem_read_in = 0;
    mem_write_in = 0;
    mem_to_reg_in = 0;
    branch_in = 1;

    #10;

    $finish;
end

endmodule

ex_mem.vcd
$date
	Sat Sep 12 23:48:49 2026
$end
$version
	Icarus Verilog
$end
$timescale
	1ps
$end
$scope module tb_ex_mem $end
$var wire 1 ! zero_out $end
$var wire 32 " write_data_out [31:0] $end
$var wire 1 # reg_write_out $end
$var wire 5 $ rd_out [4:0] $end
$var wire 1 % mem_write_out $end
$var wire 1 & mem_to_reg_out $end
$var wire 1 ' mem_read_out $end
$var wire 32 ( branch_target_out [31:0] $end
$var wire 1 ) branch_out $end
$var wire 32 * alu_result_out [31:0] $end
$var reg 32 + alu_result_in [31:0] $end
$var reg 1 , branch_in $end
$var reg 32 - branch_target_in [31:0] $end
$var reg 1 . clk $end
$var reg 1 / mem_read_in $end
$var reg 1 0 mem_to_reg_in $end
$var reg 1 1 mem_write_in $end
$var reg 5 2 rd_in [4:0] $end
$var reg 1 3 reg_write_in $end
$var reg 1 4 rst $end
$var reg 32 5 write_data_in [31:0] $end
$var reg 1 6 zero_in $end
$scope module uut $end
$var wire 32 7 alu_result_in [31:0] $end
$var wire 1 , branch_in $end
$var wire 32 8 branch_target_in [31:0] $end
$var wire 1 . clk $end
$var wire 1 / mem_read_in $end
$var wire 1 0 mem_to_reg_in $end
$var wire 1 1 mem_write_in $end
$var wire 5 9 rd_in [4:0] $end
$var wire 1 3 reg_write_in $end
$var wire 1 4 rst $end
$var wire 32 : write_data_in [31:0] $end
$var wire 1 6 zero_in $end
$var reg 32 ; alu_result_out [31:0] $end
$var reg 1 ) branch_out $end
$var reg 32 < branch_target_out [31:0] $end
$var reg 1 ' mem_read_out $end
$var reg 1 & mem_to_reg_out $end
$var reg 1 % mem_write_out $end
$var reg 5 = rd_out [4:0] $end
$var reg 1 # reg_write_out $end
$var reg 32 > write_data_out [31:0] $end
$var reg 1 ! zero_out $end
$upscope $end
$upscope $end
$enddefinitions $end
$comment Show the parameter values. $end
$dumpall
$end
#0
$dumpvars
bx >
bx =
bx <
bx ;
b0 :
b0 9
b0 8
b0 7
06
b0 5
14
03
b0 2
01
00
0/
0.
b0 -
0,
b0 +
bx *
x)
bx (
x'
x&
x%
bx $
x#
bx "
x!
$end
#5000
0)
0&
0%
0'
0#
b0 $
b0 =
0!
b0 (
b0 <
b0 "
b0 >
b0 *
b0 ;
1.
#10000
0.
13
b101 2
b101 9
b101000 -
b101000 8
b11001 5
b11001 :
b1100100 +
b1100100 7
04
#15000
1#
b101 $
b101 =
b101000 (
b101000 <
b11001 "
b11001 >
b1100100 *
b1100100 ;
1.
#20000
0.
10
1/
b1010 2
b1010 9
16
b1010000 -
b1010000 8
b110010 5
b110010 :
b11001000 +
b11001000 7
#25000
1&
1'
b1010 $
b1010 =
1!
b1010000 (
b1010000 <
b110010 "
b110010 >
b11001000 *
b11001000 ;
1.
#30000
0.
00
11
0/
03
b1111 2
b1111 9
06
b1111000 -
b1111000 8
b1001011 5
b1001011 :
b100101100 +
b100101100 7
#35000
0&
1%
0'
0#
b1111 $
b1111 =
0!
b1111000 (
b1111000 <
b1001011 "
b1001011 >
b100101100 *
b100101100 ;
1.
#40000
0.
1,
01
b0 2
b0 9
16
b10100000 -
b10100000 8
b0 5
b0 :
b110010000 +
b110010000 7
#45000
1)
0%
b0 $
b0 =
1!
b10100000 (
b10100000 <
b0 "
b0 >
b110010000 *
b110010000 ;
1.
