if_id.v
module if_id (
    input wire clk,
    input wire rst,
    input wire [31:0] pc_in,
    input wire [31:0] pc_plus4_in,
    input wire [31:0] instruction_in,
    output reg [31:0] pc_out,
    output reg [31:0] pc_plus4_out,
    output reg [31:0] instruction_out
);

always @(posedge clk) begin
    if (rst) begin
        pc_out <= 32'b0;
        pc_plus4_out <= 32'b0;
        instruction_out <= 32'b0;
    end
    else begin
        pc_out <= pc_in;
        pc_plus4_out <= pc_plus4_in;
        instruction_out <= instruction_in;
    end
end

endmodule

tb_if_id.v
`timescale 1ns/1ps

module tb_if_id;

reg clk;
reg rst;
reg [31:0] pc_in;
reg [31:0] pc_plus4_in;
reg [31:0] instruction_in;

wire [31:0] pc_out;
wire [31:0] pc_plus4_out;
wire [31:0] instruction_out;

if_id uut (
    .clk(clk),
    .rst(rst),
    .pc_in(pc_in),
    .pc_plus4_in(pc_plus4_in),
    .instruction_in(instruction_in),
    .pc_out(pc_out),
    .pc_plus4_out(pc_plus4_out),
    .instruction_out(instruction_out)
);

always #5 clk = ~clk;

initial begin
    $dumpfile("if_id.vcd");
    $dumpvars(0, tb_if_id);

    clk = 0;
    rst = 1;
    pc_in = 0;
    pc_plus4_in = 0;
    instruction_in = 0;

    #10;

    rst = 0;
    pc_in = 32'h00000000;
    pc_plus4_in = 32'h00000004;
    instruction_in = 32'h00500093;

    #10;

    pc_in = 32'h00000004;
    pc_plus4_in = 32'h00000008;
    instruction_in = 32'h00A00113;

    #10;

    pc_in = 32'h00000008;
    pc_plus4_in = 32'h0000000C;
    instruction_in = 32'h002081B3;

    #10;

    pc_in = 32'h0000000C;
    pc_plus4_in = 32'h00000010;
    instruction_in = 32'h00310233;

    #10;

    $finish;
end

endmodule

if_id.vcd
$date
	Sat Sep 12 23:22:17 2026
$end
$version
	Icarus Verilog
$end
$timescale
	1ps
$end
$scope module tb_if_id $end
$var wire 32 ! pc_plus4_out [31:0] $end
$var wire 32 " pc_out [31:0] $end
$var wire 32 # instruction_out [31:0] $end
$var reg 1 $ clk $end
$var reg 32 % instruction_in [31:0] $end
$var reg 32 & pc_in [31:0] $end
$var reg 32 ' pc_plus4_in [31:0] $end
$var reg 1 ( rst $end
$scope module uut $end
$var wire 1 $ clk $end
$var wire 32 ) instruction_in [31:0] $end
$var wire 32 * pc_in [31:0] $end
$var wire 32 + pc_plus4_in [31:0] $end
$var wire 1 ( rst $end
$var reg 32 , instruction_out [31:0] $end
$var reg 32 - pc_out [31:0] $end
$var reg 32 . pc_plus4_out [31:0] $end
$upscope $end
$upscope $end
$enddefinitions $end
$comment Show the parameter values. $end
$dumpall
$end
#0
$dumpvars
bx .
bx -
bx ,
b0 +
b0 *
b0 )
1(
b0 '
b0 &
b0 %
0$
bx #
bx "
bx !
$end
#5000
b0 #
b0 ,
b0 !
b0 .
b0 "
b0 -
1$
#10000
0$
b10100000000000010010011 %
b10100000000000010010011 )
b100 '
b100 +
0(
#15000
b10100000000000010010011 #
b10100000000000010010011 ,
b100 !
b100 .
1$
#20000
0$
b101000000000000100010011 %
b101000000000000100010011 )
b1000 '
b1000 +
b100 &
b100 *
#25000
b101000000000000100010011 #
b101000000000000100010011 ,
b1000 !
b1000 .
b100 "
b100 -
1$
#30000
0$
b1000001000000110110011 %
b1000001000000110110011 )
b1100 '
b1100 +
b1000 &
b1000 *
#35000
b1000001000000110110011 #
b1000001000000110110011 ,
b1100 !
b1100 .
b1000 "
b1000 -
1$
#40000
0$
b1100010000001000110011 %
b1100010000001000110011 )
b10000 '
b10000 +
b1100 &
b1100 *
#45000
b1100010000001000110011 #
b1100010000001000110011 ,
b10000 !
b10000 .
b1100 "
b1100 -
1$
