instruction_memory.v
module instruction_memory (
    input wire [31:0] pc,
    output wire [31:0] instruction
);

reg [31:0] memory [0:255];

initial begin
    memory[0] = 32'h00500093;
    memory[1] = 32'h00A00113;
    memory[2] = 32'h002081B3;
    memory[3] = 32'h00310233;
    memory[4] = 32'h004182B3;
    memory[5] = 32'h00520333;
    memory[6] = 32'h006283B3;
    memory[7] = 32'h00730433;
end

assign instruction = memory[pc[9:2]];

endmodule

tb_instruction_memory.v
`timescale 1ns/1ps

module tb_instruction_memory;

reg [31:0] pc;
wire [31:0] instruction;

instruction_memory uut (
    .pc(pc),
    .instruction(instruction)
);

initial begin
    $dumpfile("instruction_memory.vcd");
    $dumpvars(0, tb_instruction_memory);

    pc = 32'd0;
    #10;

    pc = 32'd4;
    #10;

    pc = 32'd8;
    #10;

    pc = 32'd12;
    #10;

    pc = 32'd16;
    #10;

    pc = 32'd20;
    #10;

    pc = 32'd24;
    #10;

    pc = 32'd28;
    #10;

    $finish;
end

endmodule

instruction_memory.vcd
$date
	Sat Sep 12 23:00:13 2026
$end
$version
	Icarus Verilog
$end
$timescale
	1ps
$end
$scope module tb_instruction_memory $end
$var wire 32 ! instruction [31:0] $end
$var reg 32 " pc [31:0] $end
$scope module uut $end
$var wire 32 # instruction [31:0] $end
$var wire 32 $ pc [31:0] $end
$upscope $end
$upscope $end
$enddefinitions $end
$comment Show the parameter values. $end
$dumpall
$end
#0
$dumpvars
b0 $
b10100000000000010010011 #
b0 "
b10100000000000010010011 !
$end
#10000
b101000000000000100010011 !
b101000000000000100010011 #
b100 "
b100 $
#20000
b1000001000000110110011 !
b1000001000000110110011 #
b1000 "
b1000 $
#30000
b1100010000001000110011 !
b1100010000001000110011 #
b1100 "
b1100 $
#40000
b10000011000001010110011 !
b10000011000001010110011 #
b10000 "
b10000 $
#50000
b10100100000001100110011 !
b10100100000001100110011 #
b10100 "
b10100 $
#60000
b11000101000001110110011 !
b11000101000001110110011 #
b11000 "
b11000 $
#70000
b11100110000010000110011 !
b11100110000010000110011 #
b11100 "
b11100 $
