mem_wb.v
module mem_wb (
    input wire clk,
    input wire rst,
    input wire [31:0] read_data_in,
    input wire [31:0] alu_result_in,
    input wire [4:0] rd_in,
    input wire reg_write_in,
    input wire mem_to_reg_in,
    output reg [31:0] read_data_out,
    output reg [31:0] alu_result_out,
    output reg [4:0] rd_out,
    output reg reg_write_out,
    output reg mem_to_reg_out
);

always @(posedge clk) begin
    if (rst) begin
        read_data_out <= 32'b0;
        alu_result_out <= 32'b0;
        rd_out <= 5'b0;
        reg_write_out <= 1'b0;
        mem_to_reg_out <= 1'b0;
    end
    else begin
        read_data_out <= read_data_in;
        alu_result_out <= alu_result_in;
        rd_out <= rd_in;
        reg_write_out <= reg_write_in;
        mem_to_reg_out <= mem_to_reg_in;
    end
end

endmodule

tb_mem_wb.v
`timescale 1ns/1ps

module tb_mem_wb;

reg clk;
reg rst;
reg [31:0] read_data_in;
reg [31:0] alu_result_in;
reg [4:0] rd_in;
reg reg_write_in;
reg mem_to_reg_in;

wire [31:0] read_data_out;
wire [31:0] alu_result_out;
wire [4:0] rd_out;
wire reg_write_out;
wire mem_to_reg_out;

mem_wb uut (
    .clk(clk),
    .rst(rst),
    .read_data_in(read_data_in),
    .alu_result_in(alu_result_in),
    .rd_in(rd_in),
    .reg_write_in(reg_write_in),
    .mem_to_reg_in(mem_to_reg_in),
    .read_data_out(read_data_out),
    .alu_result_out(alu_result_out),
    .rd_out(rd_out),
    .reg_write_out(reg_write_out),
    .mem_to_reg_out(mem_to_reg_out)
);

always #5 clk = ~clk;

initial begin
    $dumpfile("mem_wb.vcd");
    $dumpvars(0, tb_mem_wb);

    clk = 0;
    rst = 1;
    read_data_in = 0;
    alu_result_in = 0;
    rd_in = 0;
    reg_write_in = 0;
    mem_to_reg_in = 0;

    #10;

    rst = 0;
    read_data_in = 32'd100;
    alu_result_in = 32'd50;
    rd_in = 5'd5;
    reg_write_in = 1;
    mem_to_reg_in = 1;

    #10;

    read_data_in = 32'd200;
    alu_result_in = 32'd75;
    rd_in = 5'd10;
    reg_write_in = 1;
    mem_to_reg_in = 0;

    #10;

    read_data_in = 32'd300;
    alu_result_in = 32'd125;
    rd_in = 5'd15;
    reg_write_in = 1;
    mem_to_reg_in = 1;

    #10;

    read_data_in = 32'd0;
    alu_result_in = 32'd400;
    rd_in = 5'd0;
    reg_write_in = 0;
    mem_to_reg_in = 0;

    #10;

    $finish;
end

endmodule

mem_wb.vcd
$date
	Sun Sep 13 00:03:05 2026
$end
$version
	Icarus Verilog
$end
$timescale
	1ps
$end
$scope module tb_mem_wb $end
$var wire 1 ! reg_write_out $end
$var wire 32 " read_data_out [31:0] $end
$var wire 5 # rd_out [4:0] $end
$var wire 1 $ mem_to_reg_out $end
$var wire 32 % alu_result_out [31:0] $end
$var reg 32 & alu_result_in [31:0] $end
$var reg 1 ' clk $end
$var reg 1 ( mem_to_reg_in $end
$var reg 5 ) rd_in [4:0] $end
$var reg 32 * read_data_in [31:0] $end
$var reg 1 + reg_write_in $end
$var reg 1 , rst $end
$scope module uut $end
$var wire 32 - alu_result_in [31:0] $end
$var wire 1 ' clk $end
$var wire 1 ( mem_to_reg_in $end
$var wire 5 . rd_in [4:0] $end
$var wire 32 / read_data_in [31:0] $end
$var wire 1 + reg_write_in $end
$var wire 1 , rst $end
$var reg 32 0 alu_result_out [31:0] $end
$var reg 1 $ mem_to_reg_out $end
$var reg 5 1 rd_out [4:0] $end
$var reg 32 2 read_data_out [31:0] $end
$var reg 1 ! reg_write_out $end
$upscope $end
$upscope $end
$enddefinitions $end
$comment Show the parameter values. $end
$dumpall
$end
#0
$dumpvars
bx 2
bx 1
bx 0
b0 /
b0 .
b0 -
1,
0+
b0 *
b0 )
0(
0'
b0 &
bx %
x$
bx #
bx "
x!
$end
#5000
0$
0!
b0 #
b0 1
b0 %
b0 0
b0 "
b0 2
1'
#10000
0'
1(
1+
b101 )
b101 .
b110010 &
b110010 -
b1100100 *
b1100100 /
0,
#15000
1$
1!
b101 #
b101 1
b110010 %
b110010 0
b1100100 "
b1100100 2
1'
#20000
0'
0(
b1010 )
b1010 .
b1001011 &
b1001011 -
b11001000 *
b11001000 /
#25000
0$
b1010 #
b1010 1
b1001011 %
b1001011 0
b11001000 "
b11001000 2
1'
#30000
0'
1(
b1111 )
b1111 .
b1111101 &
b1111101 -
b100101100 *
b100101100 /
#35000
1$
b1111 #
b1111 1
b1111101 %
b1111101 0
b100101100 "
b100101100 2
1'
#40000
0'
0(
0+
b0 )
b0 .
b110010000 &
b110010000 -
b0 *
b0 /
#45000
0$
0!
b0 #
b0 1
b110010000 %
b110010000 0
b0 "
b0 2
1'
